{
  "date": "2026-03-03",
  "title": "TODAY'S SOLANA BRIEFING",
  "subtitle": "Top links from trusted desks",
  "items": [
    {
      "type": "APPS",
      "title": "Japan prime minister Sanae Takaichi disavows Solana meme coin after it crashes by 75%",
      "category": "APPS",
      "source": "CoinDesk",
      "date": "2026-03-03",
      "url": "https://www.coindesk.com/business/2026/03/03/japan-prime-minister-sanae-takaichi-disavows-solana-meme-coin-after-it-crashes-by-75",
      "whyYouShouldCare": "The disavowal by a prominent political figure could impact Solana's reputation and investor confidence, potentially affecting its liquidity and market positioning."
    }
  ]
}