[
  {
    "id": "a9a411fb0d70d1474c2c23ff73ddecaa83ee52fe",
    "title": "Wasabi Protocol drained of $4.5 million in apparent admin key compromise",
    "url": "https://www.coindesk.com/tech/2026/04/30/wasabi-protocol-drained-for-usd4-5-million-in-apparent-admin-key-compromise",
    "source": "CoinDesk",
    "firstSeenAt": "2026-05-01T08:58:44.216Z",
    "lastSeenAt": "2026-05-01T08:58:44.216Z",
    "sectionShown": "briefing",
    "topicTags": [
      "wasabi",
      "protocol",
      "drained",
      "million",
      "apparent",
      "admin",
      "compromise",
      "exploit"
    ],
    "majorUpdate": false,
    "updateReason": null
  },
  {
    "id": "c190dca6dcbae94d10b34e46d4f7a21eaa0b6f59",
    "title": "DeFi protocol Carrot becomes first casualty of $285M Drift exploit",
    "url": "https://cointelegraph.com/news/defi-protocol-carrot-becomes-first-casualty-of-285m-drift-exploit",
    "source": "Cointelegraph",
    "firstSeenAt": "2026-05-01T08:58:44.216Z",
    "lastSeenAt": "2026-05-01T08:58:44.216Z",
    "sectionShown": "briefing",
    "topicTags": [
      "defi",
      "protocol",
      "carrot",
      "becomes",
      "first",
      "casualty",
      "285m",
      "drift"
    ],
    "majorUpdate": false,
    "updateReason": null
  },
  {
    "id": "c7f84503275b4e0aa24e1f1cc671701787c693e2",
    "title": "Visa is quietly building stablecoins into mainstream payment plumbing without you knowing",
    "url": "https://cryptoslate.com/visa-is-quietly-building-stablecoins-into-mainstream-payment-plumbing-without-you-knowing",
    "source": "CryptoSlate",
    "firstSeenAt": "2026-05-01T08:58:44.215Z",
    "lastSeenAt": "2026-05-01T08:58:44.215Z",
    "sectionShown": "briefing",
    "topicTags": [
      "visa",
      "quietly",
      "building",
      "stablecoins",
      "into",
      "mainstream",
      "payment",
      "plumbing"
    ],
    "majorUpdate": false,
    "updateReason": null
  },
  {
    "id": "698b119b9b37d179bdc0aec53eb6c51f1f95653d",
    "title": "Solana ecosystem expands institutional push with Europe-focused research arm",
    "url": "https://cointelegraph.com/news/solana-ecosystem-expands-institutional-push-europe-focused-research-arm",
    "source": "Cointelegraph",
    "firstSeenAt": "2026-04-30T20:08:10.107Z",
    "lastSeenAt": "2026-04-30T20:08:10.107Z",
    "sectionShown": "briefing",
    "topicTags": [
      "solana",
      "ecosystem",
      "expands",
      "institutional",
      "push",
      "with",
      "europe",
      "focused"
    ],
    "majorUpdate": false,
    "updateReason": null
  },
  {
    "id": "de02196d6f23f72794390b8c8a2b880029402672",
    "title": "Germany’s AllUnity expands EURAU to Solana as euro stablecoins gain traction",
    "url": "https://www.coindesk.com/business/2026/04/30/germany-s-allunity-expands-eurau-to-solana-as-euro-stablecoins-gain-traction",
    "source": "CoinDesk",
    "firstSeenAt": "2026-04-30T20:08:10.106Z",
    "lastSeenAt": "2026-04-30T20:08:10.106Z",
    "sectionShown": "briefing",
    "topicTags": [
      "germany",
      "allunity",
      "expands",
      "eurau",
      "solana",
      "euro",
      "stablecoins",
      "gain"
    ],
    "majorUpdate": false,
    "updateReason": null
  },
  {
    "id": "d0deed29a44b9df9deff46e6d7dc52525c5d8572",
    "title": "Meta’s USDC pilot shows how stablecoins could capture billions in creator payouts",
    "url": "https://cryptoslate.com/metas-usdc-pilot-shows-how-stablecoins-could-capture-billions-in-creator-payouts",
    "source": "CryptoSlate",
    "firstSeenAt": "2026-04-30T20:08:10.106Z",
    "lastSeenAt": "2026-04-30T20:08:10.106Z",
    "sectionShown": "briefing",
    "topicTags": [
      "meta",
      "usdc",
      "pilot",
      "shows",
      "stablecoins",
      "could",
      "capture",
      "billions"
    ],
    "majorUpdate": false,
    "updateReason": null
  },
  {
    "id": "84badb3ae2ff0e21b43b3977c756182dcadb6a1b",
    "title": "Bitcoin slides toward $75,000, ETH, SOL, XRP drop as oil hits four-year high",
    "url": "https://www.coindesk.com/markets/2026/04/30/bitcoin-slides-toward-usd75-000-eth-sol-xrp-drop-as-oil-hits-four-year-high",
    "source": "CoinDesk",
    "firstSeenAt": "2026-04-30T09:09:55.537Z",
    "lastSeenAt": "2026-04-30T09:09:55.537Z",
    "sectionShown": "briefing",
    "topicTags": [
      "bitcoin",
      "slides",
      "toward",
      "drop",
      "hits",
      "four",
      "year",
      "high"
    ],
    "majorUpdate": false,
    "updateReason": null
  },
  {
    "id": "bab693c955db11eeb1552cf815521237550a58d6",
    "title": "South Korea’s Shinhan Card to test real-world stablecoin payments on Solana",
    "url": "https://www.theblock.co/post/399519/shinhan-card-stablecoin-solana",
    "source": "The Block",
    "firstSeenAt": "2026-04-30T09:09:55.536Z",
    "lastSeenAt": "2026-04-30T09:09:55.536Z",
    "sectionShown": "briefing",
    "topicTags": [
      "south",
      "korea",
      "shinhan",
      "card",
      "test",
      "real",
      "world",
      "stablecoin"
    ],
    "majorUpdate": false,
    "updateReason": null
  },
  {
    "id": "f60aebf86871c27f5923e59fb9d605474a160bc1",
    "title": "Meta Launches USDC Stablecoin Creator Payouts on Solana and Polygon via Stripe",
    "url": "https://decrypt.co/366087/meta-launches-usdc-stablecoin-creator-payouts-on-solana-and-polygon-via-stripe",
    "source": "Decrypt",
    "firstSeenAt": "2026-04-30T09:09:55.536Z",
    "lastSeenAt": "2026-04-30T09:09:55.536Z",
    "sectionShown": "briefing",
    "topicTags": [
      "meta",
      "launches",
      "usdc",
      "stablecoin",
      "creator",
      "payouts",
      "solana",
      "polygon"
    ],
    "majorUpdate": false,
    "updateReason": null
  }
]