{
  "meta": {
    "generatedAt": "2026-05-20T20:58:34.837Z",
    "totalCandidates": 111,
    "solanaCandidates": 25,
    "selected": 5,
    "tweetPool": 0,
    "narrativeKeywordsCount": 0
  },
  "items": [
    {
      "id": "https://solana.com/news/bits-to-bricks-merchant-settlement-is-where-stablecoins-work-alex-wilson",
      "title": "Bits to Bricks: Merchant Settlement is Where Stablecoins Work",
      "url": "https://solana.com/news/bits-to-bricks-merchant-settlement-is-where-stablecoins-work-alex-wilson",
      "source": "Solana News",
      "publishedAt": "2026-05-20T12:00:00.000Z",
      "summary": "Alex Wilson, Co-founder and CEO of Cyclops joins Amira Valliani on Bits to Bricks to unpack how stablecoin infrastructure in the long-term bet.",
      "tags": [
        "bits",
        "bricks",
        "merchant"
      ],
      "topicBucket": "infra",
      "whyItMatters": "Keep this on radar — it can shift near-term SOL narrative and positioning.",
      "mentionCount": 0,
      "xMentions": 0,
      "who": [],
      "xWho": [],
      "mentionedBy": [],
      "matchReason": "none",
      "narrativesMatched": [],
      "premiumNarrativesMatched": [],
      "scoreBreakdown": {
        "relevanceScore": 14,
        "mentionScore": 0,
        "recencyScore": 10,
        "sourceScore": 5,
        "narrativeScore": 0,
        "premiumNarrativeScore": 0
      },
      "dedupeFingerprint": "9a9002ee2100c8fea55e5585b3c51a8f291668ae",
      "score": 29
    },
    {
      "id": "https://www.theblock.co/post/402078/kik-founders-latest-app-flipcash-first-tap-coinbase-stablecoin-as-a-service-platform",
      "title": "Kik founder’s latest app Flipcash first to tap Coinbase’s stablecoin-as-a-service platform",
      "url": "https://www.theblock.co/post/402078/kik-founders-latest-app-flipcash-first-tap-coinbase-stablecoin-as-a-service-platform",
      "source": "The Block",
      "publishedAt": "2026-05-20T18:03:38.000Z",
      "summary": "Coinbase rolled out its Custom Stablecoin platform in late 2025 to enable companies to launch branded stablecoins.",
      "tags": [
        "founder",
        "latest",
        "flipcash"
      ],
      "topicBucket": "defi",
      "whyItMatters": "Keep this on radar — it can shift near-term SOL narrative and positioning.",
      "mentionCount": 0,
      "xMentions": 0,
      "who": [],
      "xWho": [],
      "mentionedBy": [],
      "matchReason": "none",
      "narrativesMatched": [],
      "premiumNarrativesMatched": [],
      "scoreBreakdown": {
        "relevanceScore": 11,
        "mentionScore": 0,
        "recencyScore": 10,
        "sourceScore": 4,
        "narrativeScore": 0,
        "premiumNarrativeScore": 0
      },
      "dedupeFingerprint": "715885fa5334a31fee2419f19c38846cc073bf08",
      "score": 25
    },
    {
      "id": "https://solana.com/news/bits-to-bricks-stablecoins-and-the-evolution-of-us-banking-davis-hart",
      "title": "Bits to Bricks: Stablecoins and the Evolution of US Banking",
      "url": "https://solana.com/news/bits-to-bricks-stablecoins-and-the-evolution-of-us-banking-davis-hart",
      "source": "Solana News",
      "publishedAt": "2026-05-18T12:00:00.000Z",
      "summary": "Davis Hart, founder and CEO of Omnia, on the path from 4,500 US banks to 300, what stablecoins really change for American banking, and where banks still win.",
      "tags": [
        "bits",
        "bricks",
        "stablecoins"
      ],
      "topicBucket": "defi",
      "whyItMatters": "Keep this on radar — it can shift near-term SOL narrative and positioning.",
      "mentionCount": 0,
      "xMentions": 0,
      "who": [],
      "xWho": [],
      "mentionedBy": [],
      "matchReason": "none",
      "narrativesMatched": [],
      "premiumNarrativesMatched": [],
      "scoreBreakdown": {
        "relevanceScore": 14,
        "mentionScore": 0,
        "recencyScore": 6,
        "sourceScore": 5,
        "narrativeScore": 0,
        "premiumNarrativeScore": 0
      },
      "dedupeFingerprint": "6f5058e0101eaf07fb253c7cc52b7ee241b9dea0",
      "score": 25
    },
    {
      "id": "https://www.theblock.co/post/402043/moneygram-remittance-validator-stripe-tempo-blockchain",
      "title": "MoneyGram named ‘anchor remittance validator’ for Stripe-backed Tempo blockchain",
      "url": "https://www.theblock.co/post/402043/moneygram-remittance-validator-stripe-tempo-blockchain",
      "source": "The Block",
      "publishedAt": "2026-05-20T14:37:50.000Z",
      "summary": "MoneyGram will help validate remittance transactions on the Layer 1 blockchain and integrate stablecoin settlement for its global flows.",
      "tags": [
        "moneygram",
        "named",
        "anchor"
      ],
      "topicBucket": "infra",
      "whyItMatters": "Infrastructure changes here can reset risk and throughput expectations.",
      "mentionCount": 0,
      "xMentions": 0,
      "who": [],
      "xWho": [],
      "mentionedBy": [],
      "matchReason": "none",
      "narrativesMatched": [],
      "premiumNarrativesMatched": [],
      "scoreBreakdown": {
        "relevanceScore": 8,
        "mentionScore": 0,
        "recencyScore": 10,
        "sourceScore": 4,
        "narrativeScore": 0,
        "premiumNarrativeScore": 0
      },
      "dedupeFingerprint": "1a1d58d7647880b72a374ddd2703503876b7a9ea",
      "score": 22
    },
    {
      "id": "https://ambcrypto.com/drift-says-insurance-fund-deposits-remain-safe-after-exploit-backlash",
      "title": "Drift says Insurance Fund deposits remain safe after exploit backlash",
      "url": "https://ambcrypto.com/drift-says-insurance-fund-deposits-remain-safe-after-exploit-backlash",
      "source": "AMB Crypto",
      "publishedAt": "2026-05-20T15:31:49.000Z",
      "summary": "Drift Protocol says Insurance Fund deposits were not impacted by the exploit and can still be withdrawn after relaunch.",
      "tags": [
        "drift",
        "says",
        "insurance"
      ],
      "topicBucket": "general",
      "whyItMatters": "Keep this on radar — it can shift near-term SOL narrative and positioning.",
      "mentionCount": 0,
      "xMentions": 0,
      "who": [],
      "xWho": [],
      "mentionedBy": [],
      "matchReason": "none",
      "narrativesMatched": [],
      "premiumNarrativesMatched": [],
      "scoreBreakdown": {
        "relevanceScore": 8,
        "mentionScore": 0,
        "recencyScore": 10,
        "sourceScore": 1,
        "narrativeScore": 0,
        "premiumNarrativeScore": 0
      },
      "dedupeFingerprint": "86582e7655d5a9d0c240449534445fab633561aa",
      "score": 19
    }
  ]
}