{
  "meta": {
    "generatedAt": "2026-02-18T14:53:42.857Z",
    "totalCandidates": 91,
    "solanaCandidates": 20,
    "selected": 5,
    "tweetPool": 396,
    "narrativeKeywordsCount": 0
  },
  "items": [
    {
      "id": "https://www.coindesk.com/tech/2026/02/18/zora-moves-onto-solana-with-attention-markets-for-trading-internet-trends",
      "title": "Zora moves onto Solana with 'attention markets' for trading internet trends",
      "url": "https://www.coindesk.com/tech/2026/02/18/zora-moves-onto-solana-with-attention-markets-for-trading-internet-trends",
      "source": "CoinDesk",
      "publishedAt": "2026-02-18T07:55:27.000Z",
      "summary": "The creator platform’s new product lets users trade tokens linked to social-media traction, a Polymarket-style bet on vibes rather than events.",
      "tags": [
        "zora",
        "moves",
        "onto"
      ],
      "topicBucket": "general",
      "whyItMatters": "Conversation overlap is live — this is actively shaping Solana positioning.",
      "mentionCount": 3,
      "xMentions": 3,
      "who": [
        {
          "handle": "@xcombhq",
          "summary": "We're shutting down $X. following the footsteps of $SEND. launched $X in December 2024 as a fun experiment. gave 14 S...",
          "tweetUrl": "https://twitter.com/xcombhq/status/2016534733778465074",
          "matchReason": "keyword_match"
        },
        {
          "handle": "@bulletxyz",
          "summary": "Perps Trading on Solana is about to change for the better. Mainnet is live. Here's how you can get in early 👇 https:...",
          "tweetUrl": "https://twitter.com/bulletxyz/status/2021948056841990207",
          "matchReason": "keyword_match"
        },
        {
          "handle": "@jussy_world",
          "summary": "I spent 4 hours researching the best crypto jobs: (Engineers, Managers, Interns) Here are 10 of them: @nunchi - Oncha...",
          "tweetUrl": "https://twitter.com/jussy_world/status/2023096475568492879",
          "matchReason": "keyword_match"
        }
      ],
      "xWho": [
        {
          "handle": "@xcombhq",
          "summary": "We're shutting down $X. following the footsteps of $SEND. launched $X in December 2024 as a fun experiment. gave 14 S...",
          "tweetUrl": "https://twitter.com/xcombhq/status/2016534733778465074",
          "matchReason": "keyword_match"
        },
        {
          "handle": "@bulletxyz",
          "summary": "Perps Trading on Solana is about to change for the better. Mainnet is live. Here's how you can get in early 👇 https:...",
          "tweetUrl": "https://twitter.com/bulletxyz/status/2021948056841990207",
          "matchReason": "keyword_match"
        },
        {
          "handle": "@jussy_world",
          "summary": "I spent 4 hours researching the best crypto jobs: (Engineers, Managers, Interns) Here are 10 of them: @nunchi - Oncha...",
          "tweetUrl": "https://twitter.com/jussy_world/status/2023096475568492879",
          "matchReason": "keyword_match"
        }
      ],
      "mentionedBy": [
        {
          "handle": "@xcombhq",
          "linkToTweet": "https://twitter.com/xcombhq/status/2016534733778465074"
        },
        {
          "handle": "@bulletxyz",
          "linkToTweet": "https://twitter.com/bulletxyz/status/2021948056841990207"
        },
        {
          "handle": "@jussy_world",
          "linkToTweet": "https://twitter.com/jussy_world/status/2023096475568492879"
        }
      ],
      "matchReason": "keyword_match",
      "narrativesMatched": [],
      "premiumNarrativesMatched": [],
      "scoreBreakdown": {
        "relevanceScore": 5,
        "mentionScore": 60,
        "recencyScore": 10,
        "sourceScore": 4,
        "narrativeScore": 0,
        "premiumNarrativeScore": 0
      },
      "dedupeFingerprint": "3f3ad20898ea2d1dc86e4ea7ea63920cbc0d6e2c",
      "score": 79
    },
    {
      "id": "https://ambcrypto.com/solana-how-30b-in-staked-sol-unlocks-new-defi-liquidity",
      "title": "Solana: How $30B in staked SOL unlocks new DeFi liquidity",
      "url": "https://ambcrypto.com/solana-how-30b-in-staked-sol-unlocks-new-defi-liquidity",
      "source": "AMB Crypto",
      "publishedAt": "2026-02-18T08:00:03.000Z",
      "summary": "Solana unlocks staked liquidity as whales position near the critical $80 demand zone.",
      "tags": [
        "solana",
        "staked",
        "unlocks"
      ],
      "topicBucket": "tokenomics",
      "whyItMatters": "Conversation overlap is live — this is actively shaping Solana positioning.",
      "mentionCount": 3,
      "xMentions": 3,
      "who": [
        {
          "handle": "@fabianosolana",
          "summary": "I ALREADY WON 15 TIMES 10 days ago I staked 20 SOL In that time I won 1 big reward (5 SOL) and 14 small rewards (0.29...",
          "tweetUrl": "https://twitter.com/fabianosolana/status/2022688589813862873",
          "matchReason": "keyword_match"
        },
        {
          "handle": "@jussy_world",
          "summary": "It's time to buy BTC on @Solana Then use it in DeFi to make 5-10% on it cbBTC - @coinbase wBTC - @BitGo xBTC - @okx L...",
          "tweetUrl": "https://twitter.com/jussy_world/status/2023010659856990236",
          "matchReason": "keyword_match"
        },
        {
          "handle": "@vibhu",
          "summary": "Since Prop AMMs took over @solana, many say the best price for SOL is on the chain itself, but is that actually true?...",
          "tweetUrl": "https://twitter.com/vibhu/status/2023623814433706418",
          "matchReason": "keyword_match"
        }
      ],
      "xWho": [
        {
          "handle": "@fabianosolana",
          "summary": "I ALREADY WON 15 TIMES 10 days ago I staked 20 SOL In that time I won 1 big reward (5 SOL) and 14 small rewards (0.29...",
          "tweetUrl": "https://twitter.com/fabianosolana/status/2022688589813862873",
          "matchReason": "keyword_match"
        },
        {
          "handle": "@jussy_world",
          "summary": "It's time to buy BTC on @Solana Then use it in DeFi to make 5-10% on it cbBTC - @coinbase wBTC - @BitGo xBTC - @okx L...",
          "tweetUrl": "https://twitter.com/jussy_world/status/2023010659856990236",
          "matchReason": "keyword_match"
        },
        {
          "handle": "@vibhu",
          "summary": "Since Prop AMMs took over @solana, many say the best price for SOL is on the chain itself, but is that actually true?...",
          "tweetUrl": "https://twitter.com/vibhu/status/2023623814433706418",
          "matchReason": "keyword_match"
        }
      ],
      "mentionedBy": [
        {
          "handle": "@fabianosolana",
          "linkToTweet": "https://twitter.com/fabianosolana/status/2022688589813862873"
        },
        {
          "handle": "@jussy_world",
          "linkToTweet": "https://twitter.com/jussy_world/status/2023010659856990236"
        },
        {
          "handle": "@vibhu",
          "linkToTweet": "https://twitter.com/vibhu/status/2023623814433706418"
        }
      ],
      "matchReason": "keyword_match",
      "narrativesMatched": [],
      "premiumNarrativesMatched": [],
      "scoreBreakdown": {
        "relevanceScore": 21,
        "mentionScore": 44,
        "recencyScore": 10,
        "sourceScore": 1,
        "narrativeScore": 0,
        "premiumNarrativeScore": 0
      },
      "dedupeFingerprint": "a3c7db7c585878cb9450aaf21030ea227eb6735e",
      "score": 76
    },
    {
      "id": "https://www.theblock.co/post/390249/zora-launches-attention-markets-solana",
      "title": "Zora launches ‘attention markets’ on Solana",
      "url": "https://www.theblock.co/post/390249/zora-launches-attention-markets-solana",
      "source": "The Block",
      "publishedAt": "2026-02-17T18:48:24.000Z",
      "summary": "Zora, a socialfi platform closely associated with the Ethereum Layer 2 Base, is launching its new attention market platform on Solana.",
      "tags": [
        "zora",
        "launches",
        "attention"
      ],
      "topicBucket": "general",
      "whyItMatters": "Conversation overlap is live — this is actively shaping Solana positioning.",
      "mentionCount": 3,
      "xMentions": 3,
      "who": [
        {
          "handle": "@bulletxyz",
          "summary": "RT @SolanaFloor: ICYMI: @Bulletxyz launches mainnet for its perps DEX on @Solana, claiming ~250µs order execution lat...",
          "tweetUrl": "https://twitter.com/bulletxyz/status/2022879829251744179",
          "matchReason": "keyword_match"
        },
        {
          "handle": "@jussy_world",
          "summary": "I spent 4 hours researching the best crypto jobs: (Engineers, Managers, Interns) Here are 10 of them: @nunchi - Oncha...",
          "tweetUrl": "https://twitter.com/jussy_world/status/2023096475568492879",
          "matchReason": "keyword_match"
        },
        {
          "handle": "@solanasensei",
          "summary": "It's Solana News time again: - @Backpack verify for claim day - @omnipair beta is live - @debridge launches MCP - @Tr...",
          "tweetUrl": "https://twitter.com/solanasensei/status/2023638806801584341",
          "matchReason": "keyword_match"
        }
      ],
      "xWho": [
        {
          "handle": "@bulletxyz",
          "summary": "RT @SolanaFloor: ICYMI: @Bulletxyz launches mainnet for its perps DEX on @Solana, claiming ~250µs order execution lat...",
          "tweetUrl": "https://twitter.com/bulletxyz/status/2022879829251744179",
          "matchReason": "keyword_match"
        },
        {
          "handle": "@jussy_world",
          "summary": "I spent 4 hours researching the best crypto jobs: (Engineers, Managers, Interns) Here are 10 of them: @nunchi - Oncha...",
          "tweetUrl": "https://twitter.com/jussy_world/status/2023096475568492879",
          "matchReason": "keyword_match"
        },
        {
          "handle": "@solanasensei",
          "summary": "It's Solana News time again: - @Backpack verify for claim day - @omnipair beta is live - @debridge launches MCP - @Tr...",
          "tweetUrl": "https://twitter.com/solanasensei/status/2023638806801584341",
          "matchReason": "keyword_match"
        }
      ],
      "mentionedBy": [
        {
          "handle": "@bulletxyz",
          "linkToTweet": "https://twitter.com/bulletxyz/status/2022879829251744179"
        },
        {
          "handle": "@jussy_world",
          "linkToTweet": "https://twitter.com/jussy_world/status/2023096475568492879"
        },
        {
          "handle": "@solanasensei",
          "linkToTweet": "https://twitter.com/solanasensei/status/2023638806801584341"
        }
      ],
      "matchReason": "keyword_match",
      "narrativesMatched": [],
      "premiumNarrativesMatched": [],
      "scoreBreakdown": {
        "relevanceScore": 8,
        "mentionScore": 52,
        "recencyScore": 9,
        "sourceScore": 4,
        "narrativeScore": 0,
        "premiumNarrativeScore": 0
      },
      "dedupeFingerprint": "2b71d01fa5ffe8ac789591f514545d84f816791d",
      "score": 73
    },
    {
      "id": "https://decrypt.co/358304/zerolend-latest-defi-platform-to-shut-down-amid-liquidity-revenue-pressures",
      "title": "ZeroLend Latest DeFi Platform to Shut Down Amid Liquidity, Revenue Pressures",
      "url": "https://decrypt.co/358304/zerolend-latest-defi-platform-to-shut-down-amid-liquidity-revenue-pressures",
      "source": "Decrypt",
      "publishedAt": "2026-02-17T15:33:31.000Z",
      "summary": "ZeroLend cited an inability to \"generate sustainable revenue\" as it became the latest DeFi platform to wind down amid the ongoing slump.",
      "tags": [
        "zerolend",
        "latest",
        "defi"
      ],
      "topicBucket": "defi",
      "whyItMatters": "Conversation overlap is live — this is actively shaping Solana positioning.",
      "mentionCount": 3,
      "xMentions": 3,
      "who": [
        {
          "handle": "@kamino_liq",
          "summary": "Kamino Liquidity has now generated over $41M in trading fees for our users In 2022 we aimed to transform DeFi liquidi...",
          "tweetUrl": "https://twitter.com/kamino_liq/status/2023761354784747878",
          "matchReason": "keyword_match"
        },
        {
          "handle": "@therealchaseeb",
          "summary": "RT @kamino_liq: Kamino Liquidity has now generated over $41M in trading fees for our users In 2022 we aimed to transf...",
          "tweetUrl": "https://twitter.com/therealchaseeb/status/2024009597267169299",
          "matchReason": "keyword_match"
        },
        {
          "handle": "@solanasensei",
          "summary": "Jupiter now allows you to borrow against natively staked SOL without relying on liquid staking tokens. Your staking r...",
          "tweetUrl": "https://twitter.com/solanasensei/status/2024092551603700123",
          "matchReason": "keyword_match"
        }
      ],
      "xWho": [
        {
          "handle": "@kamino_liq",
          "summary": "Kamino Liquidity has now generated over $41M in trading fees for our users In 2022 we aimed to transform DeFi liquidi...",
          "tweetUrl": "https://twitter.com/kamino_liq/status/2023761354784747878",
          "matchReason": "keyword_match"
        },
        {
          "handle": "@therealchaseeb",
          "summary": "RT @kamino_liq: Kamino Liquidity has now generated over $41M in trading fees for our users In 2022 we aimed to transf...",
          "tweetUrl": "https://twitter.com/therealchaseeb/status/2024009597267169299",
          "matchReason": "keyword_match"
        },
        {
          "handle": "@solanasensei",
          "summary": "Jupiter now allows you to borrow against natively staked SOL without relying on liquid staking tokens. Your staking r...",
          "tweetUrl": "https://twitter.com/solanasensei/status/2024092551603700123",
          "matchReason": "keyword_match"
        }
      ],
      "mentionedBy": [
        {
          "handle": "@kamino_liq",
          "linkToTweet": "https://twitter.com/kamino_liq/status/2023761354784747878"
        },
        {
          "handle": "@therealchaseeb",
          "linkToTweet": "https://twitter.com/therealchaseeb/status/2024009597267169299"
        },
        {
          "handle": "@solanasensei",
          "linkToTweet": "https://twitter.com/solanasensei/status/2024092551603700123"
        }
      ],
      "matchReason": "keyword_match",
      "narrativesMatched": [],
      "premiumNarrativesMatched": [],
      "scoreBreakdown": {
        "relevanceScore": 5,
        "mentionScore": 32,
        "recencyScore": 9,
        "sourceScore": 3,
        "narrativeScore": 0,
        "premiumNarrativeScore": 0
      },
      "dedupeFingerprint": "61051e60c068dd1a1b2b3f81bb6e7915e89713fd",
      "score": 49
    },
    {
      "id": "https://www.coindesk.com/tech/2026/02/18/xrp-ledger-rolls-out-members-only-dex-for-regulated-institutions",
      "title": "XRP Ledger rolls out members-only DEX for regulated institutions",
      "url": "https://www.coindesk.com/tech/2026/02/18/xrp-ledger-rolls-out-members-only-dex-for-regulated-institutions",
      "source": "CoinDesk",
      "publishedAt": "2026-02-18T12:10:46.000Z",
      "summary": "A permissioned DEX amendment creates controlled versions of XRPL’s built-in exchange, letting approved entities decide who can place and take orders.",
      "tags": [
        "ledger",
        "rolls",
        "members"
      ],
      "topicBucket": "defi",
      "whyItMatters": "Conversation overlap is live — this is actively shaping Solana positioning.",
      "mentionCount": 1,
      "xMentions": 1,
      "who": [
        {
          "handle": "@armaniferrante",
          "summary": "In the limit, Backpack and Perp DEXs are going down completely different paths. Perp DEXs are going to eat the entire...",
          "tweetUrl": "https://twitter.com/armaniferrante/status/2023671957548658994",
          "matchReason": "keyword_match"
        }
      ],
      "xWho": [
        {
          "handle": "@armaniferrante",
          "summary": "In the limit, Backpack and Perp DEXs are going down completely different paths. Perp DEXs are going to eat the entire...",
          "tweetUrl": "https://twitter.com/armaniferrante/status/2023671957548658994",
          "matchReason": "keyword_match"
        }
      ],
      "mentionedBy": [
        {
          "handle": "@armaniferrante",
          "linkToTweet": "https://twitter.com/armaniferrante/status/2023671957548658994"
        }
      ],
      "matchReason": "keyword_match",
      "narrativesMatched": [],
      "premiumNarrativesMatched": [],
      "scoreBreakdown": {
        "relevanceScore": 8,
        "mentionScore": 10,
        "recencyScore": 10,
        "sourceScore": 4,
        "narrativeScore": 0,
        "premiumNarrativeScore": 0
      },
      "dedupeFingerprint": "b16a219149c4478d62c3b41cb4171d5b6695c23b",
      "score": 32
    }
  ]
}